agentkore/__init__.py
agentkore/apps.py
agentkore/kore.py
agentkore/management/__init__.py
agentkore/management/commands/__init__.py
agentkore/management/commands/startagent.py
django_agentkore-0.1.0.dist-info/licenses/LICENSE
django_agentkore-0.1.0.dist-info/METADATA
django_agentkore-0.1.0.dist-info/WHEEL
django_agentkore-0.1.0.dist-info/top_level.txt
django_agentkore-0.1.0.dist-info/RECORD
