Metadata-Version: 2.4
Name: django-agentkore
Version: 0.1.0
Summary: A Django extension for scaffolding and managing AI agents in Django projects
Author-email: David Lapsley <davidlapsleyio@gmail.com>
License: MIT License
Project-URL: Homepage, https://github.com/davidlapsleyio/django-agentkore
Project-URL: Repository, https://github.com/davidlapsleyio/django-agentkore.git
Requires-Python: >=3.8
License-File: LICENSE
Requires-Dist: django>=3.2
Requires-Dist: openai>=0.27.0
Dynamic: license-file
